task3/f1_fsm.sv
module f1_fsm(
    input logic clk,
    input logic rst,
    input logic en,
    output logic [8:1] data_out
);

    typedef enum {S0, S1, S2, S3, S4, S5, S6, S7, S8} f1_state;
    f1_state current_state, next_state;

    always_ff @(posedge clk, posedge rst)
        if(rst) current_state <= S0;
        else current_state <= next_state;
        
    // next state logic
    always_comb 
        case(current_state)
            S0: if(en==1'b1)    next_state = S1;
                else            next_state = current_state;
            S1: if(en==1'b1)    next_state = S2;
                else            next_state = current_state;
            S2: if(en==1'b1)    next_state = S3;
                else            next_state = current_state;
            S3: if(en==1'b1)    next_state = S4;
                else            next_state = current_state;
            S4: if(en==1'b1)    next_state = S5;
                else            next_state = current_state;
            S5: if(en==1'b1)    next_state = S6;
                else            next_state = current_state;
            S6: if(en==1'b1)    next_state = S7;
                else            next_state = current_state;
            S7: if(en==1'b1)    next_state = S8;
                else            next_state = current_state;
            S8: if(en==1'b1)    next_state = S0;
                else            next_state = current_state;
            default: next_state = S0;
        endcase

    //output logic
    always_comb
        case(current_state)
            S0: data_out = 8'b0;
            S1: data_out = 8'b1;
            S2: data_out = 8'b11;
            S3: data_out = 8'b111;
            S4: data_out = 8'b1111;
            S5: data_out = 8'b11111;
            S6: data_out = 8'b111111;
            S7: data_out = 8'b1111111;
            S8: data_out = 8'b11111111;
            default: data_out = 8'b0;
        endcase

endmodule

task3/clktick.sv
module clktick #(
	parameter WIDTH = 16
)(
  // interface signals
  input  logic             clk,      // clock 
  input  logic             rst,      // reset
  input  logic             en,       // enable signal
  input  logic [WIDTH-1:0] N,     	 // clock divided by N+1
  output logic  		       tick,     // tick output
  output logic [7:0]       data_out
);

logic [WIDTH-1:0] count;

always_ff @ (posedge clk)
    if (rst) begin
        tick <= 1'b0;
        count <= N;  
        end
    else if (en) begin
	    if (count == 0) begin
		    tick <= 1'b1;
		    count <= N;
	        end
	    else begin
		    tick <= 1'b0;
		    count <= count - 1'b1;
	        end
        end
      
f1_fsm f1_fsm(
  .clk(clk),
  .en(tick),
  .rst(rst),
  .data_out(data_out)
);

endmodule

task3/clktick.vcd
$version Generated by VerilatedVcd $end
$date Thu Nov  2 11:06:14 2023 $end
$timescale 1ps $end

 $scope module TOP $end
  $var wire 16 ) N [15:0] $end
  $var wire  1 & clk $end
  $var wire  8 + data_out [7:0] $end
  $var wire  1 ( en $end
  $var wire  1 ' rst $end
  $var wire  1 * tick $end
  $scope module clktick $end
   $var wire 16 ) N [15:0] $end
   $var wire 32 - WIDTH [31:0] $end
   $var wire  1 & clk $end
   $var wire 16 , count [15:0] $end
   $var wire  8 + data_out [7:0] $end
   $var wire  1 ( en $end
   $var wire  1 ' rst $end
   $var wire  1 * tick $end
   $scope module f1_fsm $end
    $var wire  1 & clk $end
    $var wire 32 $ current_state [31:0] $end
    $var wire  8 # data_out [8:1] $end
    $var wire  1 * en $end
    $var wire 32 % next_state [31:0] $end
    $var wire  1 ' rst $end
   $upscope $end
  $upscope $end
 $upscope $end
$enddefinitions $end


#0
b00000000 #
b00000000000000000000000000000000 $
b00000000000000000000000000000000 %
1&
0'
0(
b0000000000110010 )
0*
b00000000 +
b0000000000000000 ,
b00000000000000000000000000010000 -
#1
0&
#2
1&
1'
#3
0&
#4
1&
b0000000000110010 ,
#5
0&
#6
1&
0'
#7
0&
#8
1&
1(
#9
0&
#10
1&
b0000000000110001 ,
#11
0&
#12
1&
b0000000000110000 ,
#13
0&
#14
1&
b0000000000101111 ,
#15
0&
#16
1&
b0000000000101110 ,
#17
0&
#18
1&
b0000000000101101 ,
#19
0&
#20
1&
b0000000000101100 ,
#21
0&
#22
1&
b0000000000101011 ,
#23
0&
#24
1&
b0000000000101010 ,
#25
0&
#26
1&
b0000000000101001 ,
#27
0&
#28
1&
b0000000000101000 ,
#29
0&
#30
1&
b0000000000100111 ,
#31
0&
#32
1&
b0000000000100110 ,
#33
0&
#34
1&
b0000000000100101 ,
#35
0&
#36
1&
b0000000000100100 ,
#37
0&
#38
1&
b0000000000100011 ,
#39
0&
#40
1&
b0000000000100010 ,
#41
0&
#42
1&
b0000000000100001 ,
#43
0&
#44
1&
b0000000000100000 ,
#45
0&
#46
1&
b0000000000011111 ,
#47
0&
#48
1&
b0000000000011110 ,
#49
0&
#50
1&
b0000000000011101 ,
#51
0&
#52
1&
b0000000000011100 ,
#53
0&
#54
1&
b0000000000011011 ,
#55
0&
#56
1&
b0000000000011010 ,
#57
0&
#58
1&
b0000000000011001 ,
#59
0&
#60
1&
b0000000000011000 ,
#61
0&
#62
1&
b0000000000010111 ,
#63
0&
#64
1&
b0000000000010110 ,
#65
0&
#66
1&
b0000000000010101 ,
#67
0&
#68
1&
b0000000000010100 ,
#69
0&
#70
1&
b0000000000010011 ,
#71
0&
#72
1&
b0000000000010010 ,
#73
0&
#74
1&
b0000000000010001 ,
#75
0&
#76
1&
b0000000000010000 ,
#77
0&
#78
1&
b0000000000001111 ,
#79
0&
#80
1&
b0000000000001110 ,
#81
0&
#82
1&
b0000000000001101 ,
#83
0&
#84
1&
b0000000000001100 ,
#85
0&
#86
1&
b0000000000001011 ,
#87
0&
#88
1&
b0000000000001010 ,
#89
0&
#90
1&
b0000000000001001 ,
#91
0&
#92
1&
b0000000000001000 ,
#93
0&
#94
1&
b0000000000000111 ,
#95
0&
#96
1&
b0000000000000110 ,
#97
0&
#98
1&
b0000000000000101 ,
#99
0&
#100
1&
b0000000000000100 ,
#101
0&
#102
1&
b0000000000000011 ,
#103
0&
#104
1&
b0000000000000010 ,
#105
0&
#106
1&
b0000000000000001 ,
#107
0&
#108
1&
b0000000000000000 ,
#109
0&
#110
b00000000000000000000000000000001 %
1&
1*
b0000000000110010 ,
#111
0&
#112
b00000001 #
b00000000000000000000000000000001 $
1&
0*
b00000001 +
b0000000000110001 ,
#113
0&
#114
1&
b0000000000110000 ,
#115
0&
#116
1&
b0000000000101111 ,
#117
0&
#118
1&
b0000000000101110 ,
#119
0&
#120
1&
b0000000000101101 ,
#121
0&
#122
1&
b0000000000101100 ,
#123
0&
#124
1&
b0000000000101011 ,
#125
0&
#126
1&
b0000000000101010 ,
#127
0&
#128
1&
b0000000000101001 ,
#129
0&
#130
1&
b0000000000101000 ,
#131
0&
#132
1&
b0000000000100111 ,
#133
0&
#134
1&
b0000000000100110 ,
#135
0&
#136
1&
b0000000000100101 ,
#137
0&
#138
1&
b0000000000100100 ,
#139
0&
#140
1&
b0000000000100011 ,
#141
0&
#142
1&
b0000000000100010 ,
#143
0&
#144
1&
b0000000000100001 ,
#145
0&
#146
1&
b0000000000100000 ,
#147
0&
#148
1&
b0000000000011111 ,
#149
0&
#150
1&
b0000000000011110 ,
#151
0&
#152
1&
b0000000000011101 ,
#153
0&
#154
1&
b0000000000011100 ,
#155
0&
#156
1&
b0000000000011011 ,
#157
0&
#158
1&
b0000000000011010 ,
#159
0&
#160
1&
b0000000000011001 ,
#161
0&
#162
1&
b0000000000011000 ,
#163
0&
#164
1&
b0000000000010111 ,
#165
0&
#166
1&
b0000000000010110 ,
#167
0&
#168
1&
b0000000000010101 ,
#169
0&
#170
1&
b0000000000010100 ,
#171
0&
#172
1&
b0000000000010011 ,
#173
0&
#174
1&
b0000000000010010 ,
#175
0&
#176
1&
b0000000000010001 ,
#177
0&
#178
1&
b0000000000010000 ,
#179
0&
#180
1&
b0000000000001111 ,
#181
0&
#182
1&
b0000000000001110 ,
#183
0&
#184
1&
b0000000000001101 ,
#185
0&
#186
1&
b0000000000001100 ,
#187
0&
#188
1&
b0000000000001011 ,
#189
0&
#190
1&
b0000000000001010 ,
#191
0&
#192
1&
b0000000000001001 ,
#193
0&
#194
1&
b0000000000001000 ,
#195
0&
#196
1&
b0000000000000111 ,
#197
0&
#198
1&
b0000000000000110 ,
#199
0&
#200
1&
b0000000000000101 ,
#201
0&
#202
1&
b0000000000000100 ,
#203
0&
#204
1&
b0000000000000011 ,
#205
0&
#206
1&
b0000000000000010 ,
#207
0&
#208
1&
b0000000000000001 ,
#209
0&
#210
1&
b0000000000000000 ,
#211
0&
#212
b00000000000000000000000000000010 %
1&
1*
b0000000000110010 ,
#213
0&
#214
b00000011 #
b00000000000000000000000000000010 $
1&
0*
b00000011 +
b0000000000110001 ,
#215
0&
#216
1&
b0000000000110000 ,
#217
0&
#218
1&
b0000000000101111 ,
#219
0&
#220
1&
b0000000000101110 ,
#221
0&
#222
1&
b0000000000101101 ,
#223
0&
#224
1&
b0000000000101100 ,
#225
0&
#226
1&
b0000000000101011 ,
#227
0&
#228
1&
b0000000000101010 ,
#229
0&
#230
1&
b0000000000101001 ,
#231
0&
#232
1&
b0000000000101000 ,
#233
0&
#234
1&
b0000000000100111 ,
#235
0&
#236
1&
b0000000000100110 ,
#237
0&
#238
1&
b0000000000100101 ,
#239
0&
#240
1&
b0000000000100100 ,
#241
0&
#242
1&
b0000000000100011 ,
#243
0&
#244
1&
b0000000000100010 ,
#245
0&
#246
1&
b0000000000100001 ,
#247
0&
#248
1&
b0000000000100000 ,
#249
0&
#250
1&
b0000000000011111 ,
#251
0&
#252
1&
b0000000000011110 ,
#253
0&
#254
1&
b0000000000011101 ,
#255
0&
#256
1&
b0000000000011100 ,
#257
0&
#258
1&
b0000000000011011 ,
#259
0&
#260
1&
b0000000000011010 ,
#261
0&
#262
1&
b0000000000011001 ,
#263
0&
#264
1&
b0000000000011000 ,
#265
0&
#266
1&
b0000000000010111 ,
#267
0&
#268
1&
b0000000000010110 ,
#269
0&
#270
1&
b0000000000010101 ,
#271
0&
#272
1&
b0000000000010100 ,
#273
0&
#274
1&
b0000000000010011 ,
#275
0&
#276
1&
b0000000000010010 ,
#277
0&
#278
1&
b0000000000010001 ,
#279
0&
#280
1&
b0000000000010000 ,
#281
0&
#282
1&
b0000000000001111 ,
#283
0&
#284
1&
b0000000000001110 ,
#285
0&
#286
1&
b0000000000001101 ,
#287
0&
#288
1&
b0000000000001100 ,
#289
0&
#290
1&
b0000000000001011 ,
#291
0&
#292
1&
b0000000000001010 ,
#293
0&
#294
1&
b0000000000001001 ,
#295
0&
#296
1&
b0000000000001000 ,
#297
0&
#298
1&
b0000000000000111 ,
#299
0&
#300
1&
b0000000000000110 ,
#301
0&
#302
1&
b0000000000000101 ,
#303
0&
#304
1&
b0000000000000100 ,
#305
0&
#306
1&
b0000000000000011 ,
#307
0&
#308
1&
b0000000000000010 ,
#309
0&
#310
1&
b0000000000000001 ,
#311
0&
#312
1&
b0000000000000000 ,
#313
0&
#314
b00000000000000000000000000000011 %
1&
1*
b0000000000110010 ,
#315
0&
#316
b00000111 #
b00000000000000000000000000000011 $
1&
0*
b00000111 +
b0000000000110001 ,
#317
0&
#318
1&
b0000000000110000 ,
#319
0&
#320
1&
b0000000000101111 ,
#321
0&
#322
1&
b0000000000101110 ,
#323
0&
#324
1&
b0000000000101101 ,
#325
0&
#326
1&
b0000000000101100 ,
#327
0&
#328
1&
b0000000000101011 ,
#329
0&
#330
1&
b0000000000101010 ,
#331
0&
#332
1&
b0000000000101001 ,
#333
0&
#334
1&
b0000000000101000 ,
#335
0&
#336
1&
b0000000000100111 ,
#337
0&
#338
1&
b0000000000100110 ,
#339
0&
#340
1&
b0000000000100101 ,
#341
0&
#342
1&
b0000000000100100 ,
#343
0&
#344
1&
b0000000000100011 ,
#345
0&
#346
1&
b0000000000100010 ,
#347
0&
#348
1&
b0000000000100001 ,
#349
0&
#350
1&
b0000000000100000 ,
#351
0&
#352
1&
b0000000000011111 ,
#353
0&
#354
1&
b0000000000011110 ,
#355
0&
#356
1&
b0000000000011101 ,
#357
0&
#358
1&
b0000000000011100 ,
#359
0&
#360
1&
b0000000000011011 ,
#361
0&
#362
1&
b0000000000011010 ,
#363
0&
#364
1&
b0000000000011001 ,
#365
0&
#366
1&
b0000000000011000 ,
#367
0&
#368
1&
b0000000000010111 ,
#369
0&
#370
1&
b0000000000010110 ,
#371
0&
#372
1&
b0000000000010101 ,
#373
0&
#374
1&
b0000000000010100 ,
#375
0&
#376
1&
b0000000000010011 ,
#377
0&
#378
1&
b0000000000010010 ,
#379
0&
#380
1&
b0000000000010001 ,
#381
0&
#382
1&
b0000000000010000 ,
#383
0&
#384
1&
b0000000000001111 ,
#385
0&
#386
1&
b0000000000001110 ,
#387
0&
#388
1&
b0000000000001101 ,
#389
0&
#390
1&
b0000000000001100 ,
#391
0&
#392
1&
b0000000000001011 ,
#393
0&
#394
1&
b0000000000001010 ,
#395
0&
#396
1&
b0000000000001001 ,
#397
0&
#398
1&
b0000000000001000 ,
#399
0&
#400
1&
b0000000000000111 ,
#401
0&
#402
1&
b0000000000000110 ,
#403
0&
#404
1&
b0000000000000101 ,
#405
0&
#406
1&
b0000000000000100 ,
#407
0&
#408
1&
b0000000000000011 ,
#409
0&
#410
1&
b0000000000000010 ,
#411
0&
#412
1&
b0000000000000001 ,
#413
0&
#414
1&
b0000000000000000 ,
#415
0&
#416
b00000000000000000000000000000100 %
1&
1*
b0000000000110010 ,
#417
0&
#418
b00001111 #
b00000000000000000000000000000100 $
1&
0*
b00001111 +
b0000000000110001 ,
#419
0&
#420
1&
b0000000000110000 ,
#421
0&
#422
1&
b0000000000101111 ,
#423
0&
#424
1&
b0000000000101110 ,
#425
0&
#426
1&
b0000000000101101 ,
#427
0&
#428
1&
b0000000000101100 ,
#429
0&
#430
1&
b0000000000101011 ,
#431
0&
#432
1&
b0000000000101010 ,
#433
0&
#434
1&
b0000000000101001 ,
#435
0&
#436
1&
b0000000000101000 ,
#437
0&
#438
1&
b0000000000100111 ,
#439
0&
#440
1&
b0000000000100110 ,
#441
0&
#442
1&
b0000000000100101 ,
#443
0&
#444
1&
b0000000000100100 ,
#445
0&
#446
1&
b0000000000100011 ,
#447
0&
#448
1&
b0000000000100010 ,
#449
0&
#450
1&
b0000000000100001 ,
#451
0&
#452
1&
b0000000000100000 ,
#453
0&
#454
1&
b0000000000011111 ,
#455
0&
#456
1&
b0000000000011110 ,
#457
0&
#458
1&
b0000000000011101 ,
#459
0&
#460
1&
b0000000000011100 ,
#461
0&
#462
1&
b0000000000011011 ,
#463
0&
#464
1&
b0000000000011010 ,
#465
0&
#466
1&
b0000000000011001 ,
#467
0&
#468
1&
b0000000000011000 ,
#469
0&
#470
1&
b0000000000010111 ,
#471
0&
#472
1&
b0000000000010110 ,
#473
0&
#474
1&
b0000000000010101 ,
#475
0&
#476
1&
b0000000000010100 ,
#477
0&
#478
1&
b0000000000010011 ,
#479
0&
#480
1&
b0000000000010010 ,
#481
0&
#482
1&
b0000000000010001 ,
#483
0&
#484
1&
b0000000000010000 ,
#485
0&
#486
1&
b0000000000001111 ,
#487
0&
#488
1&
b0000000000001110 ,
#489
0&
#490
1&
b0000000000001101 ,
#491
0&
#492
1&
b0000000000001100 ,
#493
0&
#494
1&
b0000000000001011 ,
#495
0&
#496
1&
b0000000000001010 ,
#497
0&
#498
1&
b0000000000001001 ,
#499
0&
#500
1&
b0000000000001000 ,
#501
0&
#502
1&
b0000000000000111 ,
#503
0&
#504
1&
b0000000000000110 ,
#505
0&
#506
1&
b0000000000000101 ,
#507
0&
#508
1&
b0000000000000100 ,
#509
0&
#510
1&
b0000000000000011 ,
#511
0&
#512
1&
b0000000000000010 ,
#513
0&
#514
1&
b0000000000000001 ,
#515
0&
#516
1&
b0000000000000000 ,
#517
0&
#518
b00000000000000000000000000000101 %
1&
1*
b0000000000110010 ,
#519
0&
#520
b00011111 #
b00000000000000000000000000000101 $
1&
0*
b00011111 +
b0000000000110001 ,
#521
0&
#522
1&
b0000000000110000 ,
#523
0&
#524
1&
b0000000000101111 ,
#525
0&
#526
1&
b0000000000101110 ,
#527
0&
#528
1&
b0000000000101101 ,
#529
0&
#530
1&
b0000000000101100 ,
#531
0&
#532
1&
b0000000000101011 ,
#533
0&
#534
1&
b0000000000101010 ,
#535
0&
#536
1&
b0000000000101001 ,
#537
0&
#538
1&
b0000000000101000 ,
#539
0&
#540
1&
b0000000000100111 ,
#541
0&
#542
1&
b0000000000100110 ,
#543
0&
#544
1&
b0000000000100101 ,
#545
0&
#546
1&
b0000000000100100 ,
#547
0&
#548
1&
b0000000000100011 ,
#549
0&
#550
1&
b0000000000100010 ,
#551
0&
#552
1&
b0000000000100001 ,
#553
0&
#554
1&
b0000000000100000 ,
#555
0&
#556
1&
b0000000000011111 ,
#557
0&
#558
1&
b0000000000011110 ,
#559
0&
#560
1&
b0000000000011101 ,
#561
0&
#562
1&
b0000000000011100 ,
#563
0&
#564
1&
b0000000000011011 ,
#565
0&
#566
1&
b0000000000011010 ,
#567
0&
#568
1&
b0000000000011001 ,
#569
0&
#570
1&
b0000000000011000 ,
#571
0&
#572
1&
b0000000000010111 ,
#573
0&
#574
1&
b0000000000010110 ,
#575
0&
#576
1&
b0000000000010101 ,
#577
0&
#578
1&
b0000000000010100 ,
#579
0&
#580
1&
b0000000000010011 ,
#581
0&
#582
1&
b0000000000010010 ,
#583
0&
#584
1&
b0000000000010001 ,
#585
0&
#586
1&
b0000000000010000 ,
#587
0&
#588
1&
b0000000000001111 ,
#589
0&
#590
1&
b0000000000001110 ,
#591
0&
#592
1&
b0000000000001101 ,
#593
0&
#594
1&
b0000000000001100 ,
#595
0&
#596
1&
b0000000000001011 ,
#597
0&
#598
1&
b0000000000001010 ,
#599
0&
#600
1&
b0000000000001001 ,
#601
0&
#602
1&
b0000000000001000 ,
#603
0&
#604
1&
b0000000000000111 ,
#605
0&
#606
1&
b0000000000000110 ,
#607
0&
#608
1&
b0000000000000101 ,
#609
0&
#610
1&
b0000000000000100 ,
#611
0&
#612
1&
b0000000000000011 ,
#613
0&
#614
1&
b0000000000000010 ,
#615
0&
#616
1&
b0000000000000001 ,
#617
0&
#618
1&
b0000000000000000 ,
#619
0&
#620
b00000000000000000000000000000110 %
1&
1*
b0000000000110010 ,
#621
0&
#622
b00111111 #
b00000000000000000000000000000110 $
1&
0*
b00111111 +
b0000000000110001 ,
#623
0&
#624
1&
b0000000000110000 ,
#625
0&
#626
1&
b0000000000101111 ,
#627
0&
#628
1&
b0000000000101110 ,
#629
0&
#630
1&
b0000000000101101 ,
#631
0&
#632
1&
b0000000000101100 ,
#633
0&
#634
1&
b0000000000101011 ,
#635
0&
#636
1&
b0000000000101010 ,
#637
0&
#638
1&
b0000000000101001 ,
#639
0&
#640
1&
b0000000000101000 ,
#641
0&
#642
1&
b0000000000100111 ,
#643
0&
#644
1&
b0000000000100110 ,
#645
0&
#646
1&
b0000000000100101 ,
#647
0&
#648
1&
b0000000000100100 ,
#649
0&
#650
1&
b0000000000100011 ,
#651
0&
#652
1&
b0000000000100010 ,
#653
0&
#654
1&
b0000000000100001 ,
#655
0&
#656
1&
b0000000000100000 ,
#657
0&
#658
1&
b0000000000011111 ,
#659
0&
#660
1&
b0000000000011110 ,
#661
0&
#662
1&
b0000000000011101 ,
#663
0&
#664
1&
b0000000000011100 ,
#665
0&
#666
1&
b0000000000011011 ,
#667
0&
#668
1&
b0000000000011010 ,
#669
0&
#670
1&
b0000000000011001 ,
#671
0&
#672
1&
b0000000000011000 ,
#673
0&
#674
1&
b0000000000010111 ,
#675
0&
#676
1&
b0000000000010110 ,
#677
0&
#678
1&
b0000000000010101 ,
#679
0&
#680
1&
b0000000000010100 ,
#681
0&
#682
1&
b0000000000010011 ,
#683
0&
#684
1&
b0000000000010010 ,
#685
0&
#686
1&
b0000000000010001 ,
#687
0&
#688
1&
b0000000000010000 ,
#689
0&
#690
1&
b0000000000001111 ,
#691
0&
#692
1&
b0000000000001110 ,
#693
0&
#694
1&
b0000000000001101 ,
#695
0&
#696
1&
b0000000000001100 ,
#697
0&
#698
1&
b0000000000001011 ,
#699
0&
#700
1&
b0000000000001010 ,
#701
0&
#702
1&
b0000000000001001 ,
#703
0&
#704
1&
b0000000000001000 ,
#705
0&
#706
1&
b0000000000000111 ,
#707
0&
#708
1&
b0000000000000110 ,
#709
0&
#710
1&
b0000000000000101 ,
#711
0&
#712
1&
b0000000000000100 ,
#713
0&
#714
1&
b0000000000000011 ,
#715
0&
#716
1&
b0000000000000010 ,
#717
0&
#718
1&
b0000000000000001 ,
#719
0&
#720
1&
b0000000000000000 ,
#721
0&
#722
b00000000000000000000000000000111 %
1&
1*
b0000000000110010 ,
#723
0&
#724
b01111111 #
b00000000000000000000000000000111 $
1&
0*
b01111111 +
b0000000000110001 ,
#725
0&
#726
1&
b0000000000110000 ,
#727
0&
#728
1&
b0000000000101111 ,
#729
0&
#730
1&
b0000000000101110 ,
#731
0&
#732
1&
b0000000000101101 ,
#733
0&
#734
1&
b0000000000101100 ,
#735
0&
#736
1&
b0000000000101011 ,
#737
0&
#738
1&
b0000000000101010 ,
#739
0&
#740
1&
b0000000000101001 ,
#741
0&
#742
1&
b0000000000101000 ,
#743
0&
#744
1&
b0000000000100111 ,
#745
0&
#746
1&
b0000000000100110 ,
#747
0&
#748
1&
b0000000000100101 ,
#749
0&
#750
1&
b0000000000100100 ,
#751
0&
#752
1&
b0000000000100011 ,
#753
0&
#754
1&
b0000000000100010 ,
#755
0&
#756
1&
b0000000000100001 ,
#757
0&
#758
1&
b0000000000100000 ,
#759
0&
#760
1&
b0000000000011111 ,
#761
0&
#762
1&
b0000000000011110 ,
#763
0&
#764
1&
b0000000000011101 ,
#765
0&
#766
1&
b0000000000011100 ,
#767
0&
#768
1&
b0000000000011011 ,
#769
0&
#770
1&
b0000000000011010 ,
#771
0&
#772
1&
b0000000000011001 ,
#773
0&
#774
1&
b0000000000011000 ,
#775
0&
#776
1&
b0000000000010111 ,
#777
0&
#778
1&
b0000000000010110 ,
#779
0&
#780
1&
b0000000000010101 ,
#781
0&
#782
1&
b0000000000010100 ,
#783
0&
#784
1&
b0000000000010011 ,
#785
0&
#786
1&
b0000000000010010 ,
#787
0&
#788
1&
b0000000000010001 ,
#789
0&
#790
1&
b0000000000010000 ,
#791
0&
#792
1&
b0000000000001111 ,
#793
0&
#794
1&
b0000000000001110 ,
#795
0&
#796
1&
b0000000000001101 ,
#797
0&
#798
1&
b0000000000001100 ,
#799
0&
#800
1&
b0000000000001011 ,
#801
0&
#802
1&
b0000000000001010 ,
#803
0&
#804
1&
b0000000000001001 ,
#805
0&
#806
1&
b0000000000001000 ,
#807
0&
#808
1&
b0000000000000111 ,
#809
0&
#810
1&
b0000000000000110 ,
#811
0&
#812
1&
b0000000000000101 ,
#813
0&
#814
1&
b0000000000000100 ,
#815
0&
#816
1&
b0000000000000011 ,
#817
0&
#818
1&
b0000000000000010 ,
#819
0&
#820
1&
b0000000000000001 ,
#821
0&
#822
1&
b0000000000000000 ,
#823
0&
#824
b00000000000000000000000000001000 %
1&
1*
b0000000000110010 ,
#825
0&
#826
b11111111 #
b00000000000000000000000000001000 $
1&
0*
b11111111 +
b0000000000110001 ,
#827
0&
#828
1&
b0000000000110000 ,
#829
0&
#830
1&
b0000000000101111 ,
#831
0&
#832
1&
b0000000000101110 ,
#833
0&
#834
1&
b0000000000101101 ,
#835
0&
#836
1&
b0000000000101100 ,
#837
0&
#838
1&
b0000000000101011 ,
#839
0&
#840
1&
b0000000000101010 ,
#841
0&
#842
1&
b0000000000101001 ,
#843
0&
#844
1&
b0000000000101000 ,
#845
0&
#846
1&
b0000000000100111 ,
#847
0&
#848
1&
b0000000000100110 ,
#849
0&
#850
1&
b0000000000100101 ,
#851
0&
#852
1&
b0000000000100100 ,
#853
0&
#854
1&
b0000000000100011 ,
#855
0&
#856
1&
b0000000000100010 ,
#857
0&
#858
1&
b0000000000100001 ,
#859
0&
#860
1&
b0000000000100000 ,
#861
0&
#862
1&
b0000000000011111 ,
#863
0&
#864
1&
b0000000000011110 ,
#865
0&
#866
1&
b0000000000011101 ,
#867
0&
#868
1&
b0000000000011100 ,
#869
0&
#870
1&
b0000000000011011 ,
#871
0&
#872
1&
b0000000000011010 ,
#873
0&
#874
1&
b0000000000011001 ,
#875
0&
#876
1&
b0000000000011000 ,
#877
0&
#878
1&
b0000000000010111 ,
#879
0&
#880
1&
b0000000000010110 ,
#881
0&
#882
1&
b0000000000010101 ,
#883
0&
#884
1&
b0000000000010100 ,
#885
0&
#886
1&
b0000000000010011 ,
#887
0&
#888
1&
b0000000000010010 ,
#889
0&
#890
1&
b0000000000010001 ,
#891
0&
#892
1&
b0000000000010000 ,
#893
0&
#894
1&
b0000000000001111 ,
#895
0&
#896
1&
b0000000000001110 ,
#897
0&
#898
1&
b0000000000001101 ,
#899
0&
#900
1&
b0000000000001100 ,
#901
0&
#902
1&
b0000000000001011 ,
#903
0&
#904
1&
b0000000000001010 ,
#905
0&
#906
1&
b0000000000001001 ,
#907
0&
#908
1&
b0000000000001000 ,
#909
0&
#910
1&
b0000000000000111 ,
#911
0&
#912
1&
b0000000000000110 ,
#913
0&
#914
1&
b0000000000000101 ,
#915
0&
#916
1&
b0000000000000100 ,
#917
0&
#918
1&
b0000000000000011 ,
#919
0&
#920
1&
b0000000000000010 ,
#921
0&
#922
1&
b0000000000000001 ,
#923
0&
#924
1&
b0000000000000000 ,
#925
0&
#926
b00000000000000000000000000000000 %
1&
1*
b0000000000110010 ,
#927
0&
#928
b00000000 #
b00000000000000000000000000000000 $
1&
0*
b00000000 +
b0000000000110001 ,
#929
0&
#930
1&
b0000000000110000 ,
#931
0&
#932
1&
b0000000000101111 ,
#933
0&
#934
1&
b0000000000101110 ,
#935
0&
#936
1&
b0000000000101101 ,
#937
0&
#938
1&
b0000000000101100 ,
#939
0&
#940
1&
b0000000000101011 ,
#941
0&
#942
1&
b0000000000101010 ,
#943
0&
#944
1&
b0000000000101001 ,
#945
0&
#946
1&
b0000000000101000 ,
#947
0&
#948
1&
b0000000000100111 ,
#949
0&
#950
1&
b0000000000100110 ,
#951
0&
#952
1&
b0000000000100101 ,
#953
0&
#954
1&
b0000000000100100 ,
#955
0&
#956
1&
b0000000000100011 ,
#957
0&
#958
1&
b0000000000100010 ,
#959
0&
#960
1&
b0000000000100001 ,
#961
0&
#962
1&
b0000000000100000 ,
#963
0&
#964
1&
b0000000000011111 ,
#965
0&
#966
1&
b0000000000011110 ,
#967
0&
#968
1&
b0000000000011101 ,
#969
0&
#970
1&
b0000000000011100 ,
#971
0&
#972
1&
b0000000000011011 ,
#973
0&
#974
1&
b0000000000011010 ,
#975
0&
#976
1&
b0000000000011001 ,
#977
0&
#978
1&
b0000000000011000 ,
#979
0&
#980
1&
b0000000000010111 ,
#981
0&
#982
1&
b0000000000010110 ,
#983
0&
#984
1&
b0000000000010101 ,
#985
0&
#986
1&
b0000000000010100 ,
#987
0&
#988
1&
b0000000000010011 ,
#989
0&
#990
1&
b0000000000010010 ,
#991
0&
#992
1&
b0000000000010001 ,
#993
0&
#994
1&
b0000000000010000 ,
#995
0&
#996
1&
b0000000000001111 ,
#997
0&
#998
1&
b0000000000001110 ,
#999
0&
#1000
1&
b0000000000001101 ,
#1001
0&
#1002
1&
b0000000000001100 ,
#1003
0&
#1004
1&
b0000000000001011 ,
#1005
0&
#1006
1&
b0000000000001010 ,
#1007
0&
#1008
1&
b0000000000001001 ,
#1009
0&
#1010
1&
b0000000000001000 ,
#1011
0&
#1012
1&
b0000000000000111 ,
#1013
0&
#1014
1&
b0000000000000110 ,
#1015
0&
#1016
1&
b0000000000000101 ,
#1017
0&
#1018
1&
b0000000000000100 ,
#1019
0&
#1020
1&
b0000000000000011 ,
#1021
0&
#1022
1&
b0000000000000010 ,
#1023
0&
#1024
1&
b0000000000000001 ,
#1025
0&
#1026
1&
b0000000000000000 ,
#1027
0&
#1028
b00000000000000000000000000000001 %
1&
1*
b0000000000110010 ,
#1029
0&
#1030
b00000001 #
b00000000000000000000000000000001 $
1&
0*
b00000001 +
b0000000000110001 ,
#1031
0&
#1032
1&
b0000000000110000 ,
#1033
0&
#1034
1&
b0000000000101111 ,
#1035
0&
#1036
1&
b0000000000101110 ,
#1037
0&
#1038
1&
b0000000000101101 ,
#1039
0&
#1040
1&
b0000000000101100 ,
#1041
0&
#1042
1&
b0000000000101011 ,
#1043
0&
#1044
1&
b0000000000101010 ,
#1045
0&
#1046
1&
b0000000000101001 ,
#1047
0&
#1048
1&
b0000000000101000 ,
#1049
0&
#1050
1&
b0000000000100111 ,
#1051
0&
#1052
1&
b0000000000100110 ,
#1053
0&
#1054
1&
b0000000000100101 ,
#1055
0&
#1056
1&
b0000000000100100 ,
#1057
0&
#1058
1&
b0000000000100011 ,
#1059
0&
#1060
1&
b0000000000100010 ,
#1061
0&
#1062
1&
b0000000000100001 ,
#1063
0&
#1064
1&
b0000000000100000 ,
#1065
0&
#1066
1&
b0000000000011111 ,
#1067
0&
#1068
1&
b0000000000011110 ,
#1069
0&
#1070
1&
b0000000000011101 ,
#1071
0&
#1072
1&
b0000000000011100 ,
#1073
0&
#1074
1&
b0000000000011011 ,
#1075
0&
#1076
1&
b0000000000011010 ,
#1077
0&
#1078
1&
b0000000000011001 ,
#1079
0&
#1080
1&
b0000000000011000 ,
#1081
0&
#1082
1&
b0000000000010111 ,
#1083
0&
#1084
1&
b0000000000010110 ,
#1085
0&
#1086
1&
b0000000000010101 ,
#1087
0&
#1088
1&
b0000000000010100 ,
#1089
0&
#1090
1&
b0000000000010011 ,
#1091
0&
#1092
1&
b0000000000010010 ,
#1093
0&
#1094
1&
b0000000000010001 ,
#1095
0&
#1096
1&
b0000000000010000 ,
#1097
0&
#1098
1&
b0000000000001111 ,
#1099
0&
#1100
1&
b0000000000001110 ,
#1101
0&
#1102
1&
b0000000000001101 ,
#1103
0&
#1104
1&
b0000000000001100 ,
#1105
0&
#1106
1&
b0000000000001011 ,
#1107
0&
#1108
1&
b0000000000001010 ,
#1109
0&
#1110
1&
b0000000000001001 ,
#1111
0&
#1112
1&
b0000000000001000 ,
#1113
0&
